{"sections":{"slideshow_tBgWEc":{"type":"slideshow","blocks":{"image_mndb4t":{"type":"image","settings":{"image":"shopify:\/\/shop_images\/15__Off_Landing_Page_-_new.png","mobile_image":"shopify:\/\/shop_images\/1.jpg","hide-text":false,"title":"","text":"","button_label":"Shop Now","button_link":"","image_fit":"cover","slide-background":"#ffffff","slide-overlay":"#000000","slide-background-transparency":0,"caption-background":"rgba(0,0,0,0)","caption-text":"#ffffff","button-text":"#ffffff","button-background":"#000000","captionHorizontal":"right","captionAlignment":"right"}},"image_QXDPEi":{"type":"image","settings":{"image":"shopify:\/\/shop_images\/Summer_Soiree_landing_page_-_new.png","mobile_image":"shopify:\/\/shop_images\/Copy_of_Slim_Aarons_Ads.png","hide-text":false,"title":"","text":"","button_label":"Shop Now","button_link":"","image_fit":"cover","slide-background":"#ffffff","slide-overlay":"#000000","slide-background-transparency":0,"caption-background":"rgba(0,0,0,0)","caption-text":"#ffffff","button-text":"#ffffff","button-background":"#000000","captionHorizontal":"right","captionAlignment":"right"}},"image_qwGd3m":{"type":"image","settings":{"image":"shopify:\/\/shop_images\/shop_now_landing_page_-_new.png","mobile_image":"shopify:\/\/shop_images\/2.jpg","hide-text":false,"title":"","text":"","button_label":"Shop Now","button_link":"","image_fit":"cover","slide-background":"#ffffff","slide-overlay":"#000000","slide-background-transparency":0,"caption-background":"rgba(0,0,0,0)","caption-text":"#ffffff","button-text":"#ffffff","button-background":"#000000","captionHorizontal":"right","captionAlignment":"right"}}},"block_order":["image_mndb4t","image_QXDPEi","image_qwGd3m"],"settings":{"slider-animation":"fade","slider-width":"full-width","slider-slide-time":3,"caption-heading-size":30,"caption-subheading-size":16,"caption-button-size":14,"show-slide-dots":true,"show-slide-arrows":false,"slider-navigation-color":"#ffffff"}},"rich_text_X6KUqi":{"type":"rich-text","custom_css":["h2 {text-align: center;}","p {text-align: left;}"],"settings":{"colors":"white","title":"Slim Aarons - Summer Soirée","text":"<p>On Thursday 29th August, Enter Gallery is hosting our Slim Aarons Summer Soiree. On the night, we’ll be honouring the beautiful work of iconic photographer, Slim Aarons – an artist known as ‘the guru of 21st century cool’, whose sun-kissed works capture, “attractive people doing attractive things in attractive places.” <\/p>","button_label":"Sign-Up Via EventBrite","button_link":"https:\/\/www.eventbrite.co.uk\/e\/slim-aarons-summer-soiree-tickets-951427263557"}},"feature_row_DGXPyM":{"type":"feature-row","custom_css":["h2 {text-align: center;}","p {font-size: 16px; text-align: left;}"],"settings":{"colors":"light","image":"shopify:\/\/shop_images\/Slim_Aarons_Ads_800_x_600_px_2.gif","parallax":false,"text_overlapping_image":false,"layout":"left","text_alignment":"center","image_width":"small","image_height":"30vw","title":"Summer Sale","text":"<p>We’re delighted to be able to offer our clients an incredible <strong>15% off <\/strong>Slim Aarons prints, as well as an additional <strong>20% off framing<\/strong> for the duration of August. <\/p>","button_label":"Shop Now","button_link":"shopify:\/\/collections\/slim-aarons"}},"collection_products_list_eFaGVM":{"type":"collection-products-list","blocks":{"featured_collection_4gyAe9":{"type":"featured_collection","settings":{"collection":"slim-aarons-poolside","subheading":""}},"featured_collection_KpAkwV":{"type":"featured_collection","settings":{"collection":"slim-aarons-style","subheading":""}},"featured_collection_4WfMVn":{"type":"featured_collection","settings":{"collection":"slim-aarons-the-essential-collection","subheading":""}},"featured_collection_7Cc4Br":{"type":"featured_collection","settings":{"collection":"slim-aarons-la-dolce-vita","subheading":""}}},"block_order":["featured_collection_4gyAe9","featured_collection_KpAkwV","featured_collection_4WfMVn","featured_collection_7Cc4Br"],"custom_css":["img {display: block; margin-left: 150; margin-right: auto; width: 40 %;}"],"settings":{"colors":"white","title":"Slim Aarons Collections"}},"feature_row_ycUrFL":{"type":"feature-row","custom_css":["h2 {text-align: center;}"],"settings":{"colors":"white","image":"shopify:\/\/shop_images\/Brochure_mock_up_5.png","parallax":false,"text_overlapping_image":false,"layout":"left","text_alignment":"center","image_width":"small","image_height":"30vw","title":"Digital Brochure: Slim Aarons","text":"","button_label":"Request Brochure","button_link":"https:\/\/share.hsforms.com\/14oHbbqqYT4Gy61TLTrtz3g4j38d"}},"collection_products_list_mBFm86":{"type":"collection-products-list","blocks":{"featured_product_anF4Ex":{"type":"featured_product","settings":{"product":"poolside-gossip-c-type-print-ar20341"}},"featured_product_6aczYP":{"type":"featured_product","settings":{"product":"speedboat-landing-c-type-print-eg05298"}},"featured_product_eQNkjh":{"type":"featured_product","settings":{"product":"eden-roc-pool-c-type-print-ar23110"}}},"block_order":["featured_product_anF4Ex","featured_product_6aczYP","featured_product_eQNkjh"],"settings":{"colors":"white","title":"Bestsellers"}}},"order":["slideshow_tBgWEc","rich_text_X6KUqi","feature_row_DGXPyM","collection_products_list_eFaGVM","feature_row_ycUrFL","collection_products_list_mBFm86"]}